pyrgg/__init__.py
pyrgg/__main__.py
pyrgg/functions.py
pyrgg/graph_gen.py
pyrgg/params.py
pyrgg/test.py
pyrgg/engines/__init__.py
pyrgg/engines/barabasi_albert.py
pyrgg/engines/erdos_reyni.py
pyrgg/engines/erdos_reyni_gilbert.py
pyrgg/engines/pyrgg.py
pyrgg/engines/stochastic_block_model.py
pyrgg-1.8.dist-info/licenses/AUTHORS.md
pyrgg-1.8.dist-info/licenses/LICENSE
pyrgg-1.8.dist-info/METADATA
pyrgg-1.8.dist-info/WHEEL
pyrgg-1.8.dist-info/entry_points.txt
pyrgg-1.8.dist-info/top_level.txt
pyrgg-1.8.dist-info/RECORD
